{
  "id": 48,
  "name": "衰老的生物学机制",
  "core_concept": "- **要点1**：衰老是机体结构和功能随时间逐渐变化的复杂生物学过程。\n- **要点2**：细胞损伤积累、DNA变化、代谢失衡和组织修复能力下降都与衰老有关。\n- **要点3**：衰老不是单一器官变化，而是全身多系统共同变化。\n- **要点4**：生活方式会影响健康衰老的速度和质量。\n- **要点5**：研究衰老有助于理解疾病预防和健康管理。\n- **拓展理解**：学习这一知识点时，不能只停留在名词记忆上，还要结合真实情境理解它与自然环境、社会生活或科学实践之间的联系。\n- **学习提醒**：判断相关问题时，要同时关注条件、过程和结果，避免只抓住表面现象而忽略背后的因果关系。",
  "story_cases": [
    {
      "title": "案例1：为什么年纪增大后伤口恢复往往更慢",
      "content": "随着年龄增长，细胞修复和组织再生能力可能下降。 进一步分析时，可以把这一情境放回真实生活或学习场景中思考，理解事件为什么会这样发生、还会受到哪些条件影响，以及如果条件改变，结果是否也会随之变化。",
      "application": "衰老会影响组织修复效率。 这也说明，学习这一知识点时要把它和实际决策、生活经验或区域背景联系起来理解，而不是只背结论。",
      "type": "生活场景",
      "difficulty": "简单",
      "creativity": 0.78
    },
    {
      "title": "案例2：为什么保持运动被认为有助于延缓衰老影响",
      "content": "规律运动有助于维持心肺、肌肉和代谢功能，提高健康状态。 进一步分析时，可以把这一情境放回真实生活或学习场景中思考，理解事件为什么会这样发生、还会受到哪些条件影响，以及如果条件改变，结果是否也会随之变化。",
      "application": "生活方式会影响健康衰老。 这也说明，学习这一知识点时要把它和实际决策、生活经验或区域背景联系起来理解，而不是只背结论。",
      "type": "健康场景",
      "difficulty": "简单",
      "creativity": 0.79
    },
    {
      "title": "案例3：为什么衰老和某些慢性病风险相关",
      "content": "随着机体调节能力下降，一些系统更容易出现功能失衡。 进一步分析时，可以把这一情境放回真实生活或学习场景中思考，理解事件为什么会这样发生、还会受到哪些条件影响，以及如果条件改变，结果是否也会随之变化。",
      "application": "衰老研究与疾病预防相关。 这也说明，学习这一知识点时要把它和实际决策、生活经验或区域背景联系起来理解，而不是只背结论。",
      "type": "医学场景",
      "difficulty": "中等",
      "creativity": 0.82
    },
    {
      "title": "案例4：为什么科学家会研究细胞层面的衰老",
      "content": "细胞变化是组织和器官衰老的重要基础。 进一步分析时，可以把这一情境放回真实生活或学习场景中思考，理解事件为什么会这样发生、还会受到哪些条件影响，以及如果条件改变，结果是否也会随之变化。",
      "application": "宏观老化与微观机制密切相关。 这也说明，学习这一知识点时要把它和实际决策、生活经验或区域背景联系起来理解，而不是只背结论。",
      "type": "科研场景",
      "difficulty": "中等",
      "creativity": 0.81
    },
    {
      "title": "案例5：为什么“长寿”不等于“健康老去”",
      "content": "仅仅活得更久并不意味着身体功能状态良好，健康寿命同样重要。 进一步分析时，可以把这一情境放回真实生活或学习场景中思考，理解事件为什么会这样发生、还会受到哪些条件影响，以及如果条件改变，结果是否也会随之变化。",
      "application": "衰老研究不只关注寿命，也关注生活质量。 这也说明，学习这一知识点时要把它和实际决策、生活经验或区域背景联系起来理解，而不是只背结论。",
      "type": "概念辨析",
      "difficulty": "简单",
      "creativity": 0.77
    }
  ],
  "misconceptions": [
    {
      "title": "误区1：衰老只是外表变老",
      "wrong_understanding": "把衰老理解成皱纹和白发。 这种想法通常来自只看表面现象、没有结合背景条件进行分析。",
      "correct_understanding": "衰老涉及细胞、组织和多个系统功能变化。 正确理解时要把概念放回具体情境中，看到它与环境、条件和过程之间的联系。",
      "frequency": "约60%的学生有此误区",
      "typical_error": "只从外貌描述衰老。 学生在作答时常把一个现象当成全部原因，导致判断片面。",
      "exam_example": "生理变化题中常见。 这类错误在材料分析、情境判断和概念辨析题中都比较常见。"
    },
    {
      "title": "误区2：衰老完全无法被健康管理影响",
      "wrong_understanding": "把衰老看成完全不可干预。 这种想法通常来自只看表面现象、没有结合背景条件进行分析。",
      "correct_understanding": "虽然衰老不可避免，但生活方式会影响健康衰老程度。 正确理解时要把概念放回具体情境中，看到它与环境、条件和过程之间的联系。",
      "frequency": "约55%的学生有此误区",
      "typical_error": "认为养生和健康习惯毫无意义。 学生在作答时常把一个现象当成全部原因，导致判断片面。",
      "exam_example": "健康教育题中常见。 这类错误在材料分析、情境判断和概念辨析题中都比较常见。"
    },
    {
      "title": "误区3：长寿就是最重要指标",
      "wrong_understanding": "只关注寿命长度。 这种想法通常来自只看表面现象、没有结合背景条件进行分析。",
      "correct_understanding": "健康寿命和生活质量同样重要。 正确理解时要把概念放回具体情境中，看到它与环境、条件和过程之间的联系。",
      "frequency": "约47%的学生有此误区",
      "typical_error": "忽略功能状态。 学生在作答时常把一个现象当成全部原因，导致判断片面。",
      "exam_example": "生物与健康综合题中常见。 这类错误在材料分析、情境判断和概念辨析题中都比较常见。"
    }
  ],
  "error_options": [
    {
      "scenario": "理解衰老的本质",
      "correct_option": "是多系统、多层次逐渐变化的复杂过程",
      "option_number": 1,
      "option_text": "就是皮肤起皱、头发变白这么简单",
      "deception": "外表变化最容易观察。 它往往抓住了生活经验中最直观的一面，所以很容易让人第一眼觉得“似乎没错”。",
      "error_reason": "忽略内部生理机制。 本质上是把单一经验、表面现象或局部条件误当成完整解释。",
      "failure_analysis": "外表变化只是衰老的一部分表现。 更完整的分析应当回到知识点本身，结合条件、过程与结果之间的关系来判断，避免只凭直觉或经验作答。"
    },
    {
      "scenario": "评价健康习惯与衰老的关系",
      "correct_option": "良好生活方式有助于提高健康寿命和延缓衰老不良影响",
      "option_number": 2,
      "option_text": "衰老完全由年龄决定，生活习惯没意义",
      "deception": "把不可避免误解成不可管理。 它往往抓住了生活经验中最直观的一面，所以很容易让人第一眼觉得“似乎没错”。",
      "error_reason": "忽略健康管理作用。 本质上是把单一经验、表面现象或局部条件误当成完整解释。",
      "failure_analysis": "生活方式虽不能停止衰老，但能影响其质量与速度。 更完整的分析应当回到知识点本身，结合条件、过程与结果之间的关系来判断，避免只凭直觉或经验作答。"
    }
  ],
  "teaching_advice": "1. 从伤口恢复、体能变化等生活现象切入衰老机制。\n2. 强调衰老是多系统变化，不是单一外貌问题。\n3. 将运动、睡眠和饮食与健康衰老联系起来。\n4. 帮助学生建立“健康寿命”概念。"
}