{
  "id": 8,
  "name": "山地、平原、高原、盆地的特点",
  "core_concept": "- **要点1**：山地起伏大、海拔较高，平原地势平坦，高原海拔高但相对平坦，盆地四周高、中间低。\n- **要点2**：不同地形单元在气候、交通、农业和聚落方面表现不同。\n- **要点3**：山地适合发展林业、旅游和部分立体农业。\n- **要点4**：平原多利于耕作和城市建设。\n- **要点5**：高原和盆地各有独特环境条件与开发方式。\n- **拓展理解**：学习这一知识点时，不能只停留在名词记忆上，还要结合真实情境理解它与自然环境、社会生活或科学实践之间的联系。\n- **学习提醒**：判断相关问题时，要同时关注条件、过程和结果，避免只抓住表面现象而忽略背后的因果关系。",
  "story_cases": [
    {
      "title": "案例1：为什么大城市多分布在平原地区",
      "content": "平原地形平坦、交通便利、建设成本较低，更利于人口和产业集聚。 进一步分析时，可以把这一情境放回真实生活或学习场景中思考，理解事件为什么会这样发生、还会受到哪些条件影响，以及如果条件改变，结果是否也会随之变化。",
      "application": "平原对城市发展具有明显优势。 这也说明，学习这一知识点时要把它和实际决策、生活经验或区域背景联系起来理解，而不是只背结论。",
      "type": "城市场景",
      "difficulty": "简单",
      "creativity": 0.79
    },
    {
      "title": "案例2：为什么高原地区常给人“高但不一定陡”的感觉",
      "content": "高原整体海拔高，但地表相对开阔和平缓，不同于山地的剧烈起伏。 进一步分析时，可以把这一情境放回真实生活或学习场景中思考，理解事件为什么会这样发生、还会受到哪些条件影响，以及如果条件改变，结果是否也会随之变化。",
      "application": "区分高原和山地要看起伏形态。 这也说明，学习这一知识点时要把它和实际决策、生活经验或区域背景联系起来理解，而不是只背结论。",
      "type": "区域场景",
      "difficulty": "中等",
      "creativity": 0.81
    },
    {
      "title": "案例3：为什么盆地中常形成较独特的小气候",
      "content": "盆地四周较高，空气流动和热量交换有其特殊性，容易形成局地气候特点。 进一步分析时，可以把这一情境放回真实生活或学习场景中思考，理解事件为什么会这样发生、还会受到哪些条件影响，以及如果条件改变，结果是否也会随之变化。",
      "application": "地形会影响区域气候环境。 这也说明，学习这一知识点时要把它和实际决策、生活经验或区域背景联系起来理解，而不是只背结论。",
      "type": "环境场景",
      "difficulty": "中等",
      "creativity": 0.82
    },
    {
      "title": "案例4：山区为什么适合发展观光和避暑旅游",
      "content": "山地景观丰富、气温相对较低，常具有较高旅游吸引力。 进一步分析时，可以把这一情境放回真实生活或学习场景中思考，理解事件为什么会这样发生、还会受到哪些条件影响，以及如果条件改变，结果是否也会随之变化。",
      "application": "山地具备生态和景观开发价值。 这也说明，学习这一知识点时要把它和实际决策、生活经验或区域背景联系起来理解，而不是只背结论。",
      "type": "旅游场景",
      "difficulty": "简单",
      "creativity": 0.8
    },
    {
      "title": "案例5：为什么不同地形上的农业方式不一样",
      "content": "坡度、土壤、灌溉条件和交通差异会影响作物类型与农业经营方式。 进一步分析时，可以把这一情境放回真实生活或学习场景中思考，理解事件为什么会这样发生、还会受到哪些条件影响，以及如果条件改变，结果是否也会随之变化。",
      "application": "地形影响生产方式选择。 这也说明，学习这一知识点时要把它和实际决策、生活经验或区域背景联系起来理解，而不是只背结论。",
      "type": "农业场景",
      "difficulty": "中等",
      "creativity": 0.83
    }
  ],
  "misconceptions": [
    {
      "title": "误区1：海拔高的地方就一定是山地",
      "wrong_understanding": "只看海拔，不看起伏形态。 这种想法通常来自只看表面现象、没有结合背景条件进行分析。",
      "correct_understanding": "高原也可能海拔很高，但整体较平缓。 正确理解时要把概念放回具体情境中，看到它与环境、条件和过程之间的联系。",
      "frequency": "约60%的学生有此误区",
      "typical_error": "把青藏高原直接说成大山。 学生在作答时常把一个现象当成全部原因，导致判断片面。",
      "exam_example": "地形分类题中常见。 这类错误在材料分析、情境判断和概念辨析题中都比较常见。"
    },
    {
      "title": "误区2：盆地一定不适合人类居住",
      "wrong_understanding": "把盆地一概看成封闭、落后地区。 这种想法通常来自只看表面现象、没有结合背景条件进行分析。",
      "correct_understanding": "盆地是否适居要结合气候、水源、交通等条件综合分析。 正确理解时要把概念放回具体情境中，看到它与环境、条件和过程之间的联系。",
      "frequency": "约44%的学生有此误区",
      "typical_error": "只凭形状判断区域发展。 学生在作答时常把一个现象当成全部原因，导致判断片面。",
      "exam_example": "区域评价题中常见。 这类错误在材料分析、情境判断和概念辨析题中都比较常见。"
    },
    {
      "title": "误区3：平原地区所有方面都比山地好",
      "wrong_understanding": "把地形优势绝对化。 这种想法通常来自只看表面现象、没有结合背景条件进行分析。",
      "correct_understanding": "不同地形适合的发展方向不同，没有绝对优劣。 正确理解时要把概念放回具体情境中，看到它与环境、条件和过程之间的联系。",
      "frequency": "约49%的学生有此误区",
      "typical_error": "忽视山地旅游、水能等优势。 学生在作答时常把一个现象当成全部原因，导致判断片面。",
      "exam_example": "资源开发题中常见。 这类错误在材料分析、情境判断和概念辨析题中都比较常见。"
    }
  ],
  "error_options": [
    {
      "scenario": "区分高原和山地",
      "correct_option": "应同时看海拔和地表起伏程度",
      "option_number": 1,
      "option_text": "只要海拔高，就一定属于山地",
      "deception": "海拔高最容易被当作唯一标准。 它往往抓住了生活经验中最直观的一面，所以很容易让人第一眼觉得“似乎没错”。",
      "error_reason": "忽略地形分类的综合特征。 本质上是把单一经验、表面现象或局部条件误当成完整解释。",
      "failure_analysis": "高原和山地都可能海拔高，但起伏差异明显。 更完整的分析应当回到知识点本身，结合条件、过程与结果之间的关系来判断，避免只凭直觉或经验作答。"
    },
    {
      "scenario": "评价不同地形的开发价值",
      "correct_option": "不同地形适合不同产业和生活方式，不能简单比较绝对好坏",
      "option_number": 2,
      "option_text": "平原在任何情况下都比山地更有价值",
      "deception": "平原优势常更直观。 它往往抓住了生活经验中最直观的一面，所以很容易让人第一眼觉得“似乎没错”。",
      "error_reason": "忽视地形功能差异。 本质上是把单一经验、表面现象或局部条件误当成完整解释。",
      "failure_analysis": "山地、盆地、高原也有各自独特的资源和发展方向。 更完整的分析应当回到知识点本身，结合条件、过程与结果之间的关系来判断，避免只凭直觉或经验作答。"
    }
  ],
  "teaching_advice": "1. 建议用地形图片和实例帮助学生区分四类地形。\n2. 强调分类时既看海拔也看起伏。\n3. 把城市、农业和旅游与地形特征结合起来。\n4. 通过区域比较训练综合判断能力。"
}